{
    "version": "0.1.2",
    "elm-version": "0.12.3",
    "repository": "https://github.com/seliopou/elm-d3.git",
    "summary": "d3.js bindings for easy interactive diagrams and apps",
    "description": "bindings for d3.js for making composable widgets with the help of static types and FRP.",
    "license": "BSD3",
    "exposed-modules": [
        "D3",
        "D3.Color",
        "D3.Event"
    ],
    "native-modules": [
        "Native.D3.Color",
        "Native.D3.JavaScript",
        "Native.D3.Selection",
        "Native.D3.Event",
        "Native.D3.Render",
        "Native.D3.Transition"
    ],
    "dependencies": {}
}
